{
    "appKeys": {},
    "capabilities": [
        ""
    ],
    "companyName": "Xelecium Labs",
    "longName": "Pebble Batteries",
    "projectType": "native",
    "resources": {
        "media": [
            {
                "file": "fonts/Round.ttf",
                "name": "FONT_ROUND_12",
                "type": "font"
            },
            {
                "file": "fonts/Round.ttf",
                "name": "FONT_ROUND_24",
                "type": "font"
            },
            {
                "file": "fonts/Round.ttf",
                "name": "FONT_ROUND_36",
                "type": "font"
            },
            {
                "file": "images/phone_plug.png",
                "name": "IMAGE_PHONE_PLUG_ICON",
                "type": "png"
            },
            {
                "file": "images/pebble.png",
                "name": "IMAGE_PEBBLE_ICON",
                "type": "png"
            },
            {
                "file": "images/pebble_plug.png",
                "name": "IMAGE_PEBBLE_PLUG_ICON",
                "type": "png"
            },
            {
                "file": "images/disconnected.png",
                "name": "IMAGE_DISCONNECTED_ICON",
                "type": "png"
            },
            {
                "file": "images/phone.png",
                "name": "IMAGE_PHONE_ICON",
                "type": "png"
            },
            {
                "file": "images/charge.png",
                "name": "IMAGE_CHARGE_ICON",
                "type": "png"
            },
            {
                "file": "fonts/Lane.ttf",
                "name": "FONT_LANE_36",
                "type": "font"
            },
            {
                "file": "fonts/Lane.ttf",
                "name": "FONT_LANE_24",
                "type": "font"
            },
            {
                "file": "fonts/Lane.ttf",
                "name": "FONT_LANE_12",
                "type": "font"
            }
        ]
    },
    "sdkVersion": "2",
    "shortName": "PebbleBatt",
    "uuid": "1e4990c7-8abe-4643-a0fd-1d86e26503b4",
    "versionCode": 1,
    "versionLabel": "1.0",
    "watchapp": {
        "watchface": true
    }
}
